skcrf_tagger/__init__.py
skcrf_tagger/tagger.py
skcrf_tagger/utils.py
skcrf_tagger-0.0.1.dist-info/DESCRIPTION.rst
skcrf_tagger-0.0.1.dist-info/METADATA
skcrf_tagger-0.0.1.dist-info/RECORD
skcrf_tagger-0.0.1.dist-info/WHEEL
skcrf_tagger-0.0.1.dist-info/metadata.json
skcrf_tagger-0.0.1.dist-info/top_level.txt
tests/__init__.py
tests/__main__.py
tests/test_ner.py
